Lecture26/GCD_Calculator_Controller.v
module CONTROLLER(done, LdA, LdB, sel1, sel2, sel_in, start, lt, gt, eq, clk);
	input start, lt, gt, eq, clk;
	output reg done, LdA, LdB, sel1, sel2, sel_in;
	parameter S0 = 0, S1 = 1, S2 = 2, S3 = 3, S4 = 4, S5 = 5;
	reg[2:0] present_state, next_state;
	
	always @(posedge clk) begin
		present_state <= next_state;
	end
	
	always @(present_state, start, lt, gt, eq) begin
		case (present_state)
			S0: begin
				#2 if (start) begin
					next_state = S1;
					LdA = 1;
				end
			end
			S1: begin
				#2 next_state = S2;
				LdA = 0; LdB = 1;
			end
			S2: begin
				#2 if (lt) begin
					next_state = S3;
					sel1 = 1; sel2 = 0; sel_in = 1;
				end
				else if (gt) begin
					next_state = S4;
					sel1 = 0; sel2 = 1; LdA = 1; LdB = 0;
				end
				else begin
					next_state = S5;
					done = 1; LdA = 0; LdB = 0;
				end
			end
			S3: begin
				#2 if (gt) begin
					next_state = S4;
					sel1 = 0; sel2 = 1; LdA = 1; LdB = 0;
				end
				else if (eq) begin
					next_state = S5;
					done = 1; LdA = 0; LdB = 0;
				end
			end
			S4: begin
				#2 if (lt) begin
					next_state = S3;
					sel1 = 1; sel2 = 0; LdA = 0; LdB = 1;
				end
				else if (eq) begin
					next_state = S5;
					done = 1; LdA = 0; LdB = 0;
				end
			end
			S5: begin
				next_state = S5;
			end
			default: begin
				next_state = S0;
				sel1 = 0; sel2 = 0; sel_in = 0; LdA = 0; LdB = 0; done = 0;
			end
		endcase
	end
endmodule

Lecture26/GCD_Calculator_Comparator.v
module COMPARATOR(lt, gt, eq, in1, in2);
	input[15:0] in1, in2;
	output lt, gt, eq;
	
	assign lt = (in1 < in2);
	assign gt = (in1 > in2);
	assign eq = (in1 == in2);
endmodule

Lecture26/GCD_Calculator_Subtractor.v
module SUBTRACTOR(out, in1, in2);
	input[15:0] in1, in2;
	output reg[15:0] out;
	
	always @(*) begin
		out = in1 - in2;
	end
endmodule

Lecture26/GCD_Calculator_MUX.v
module MUX21(out, in1, in2, sel);
	input[15:0] in1, in2;
	input sel;
	output reg[15:0] out;
	
	always @(*) begin
		if (sel)
			out = in2;
		else
			out = in1;
	end
endmodule

Lecture26/GCD_Calculator_Register.v
module PIPO(out, in, load, clk);
	input[15:0] in;
	input load, clk;
	output reg[15:0] out;
	
	always @(posedge clk) begin
		if (load)
			out <= in;
	end
endmodule

Lecture26/GCD_Calculator_Datapath.v
module DATAPATH(lt, gt, eq, data_in, LdA, LdB, sel1, sel2, sel_in, clk);
	input[15:0] data_in;
	input LdA, LdB, sel1, sel2, sel_in, clk;
	output lt, gt, eq;
	wire[15:0] Bus, Aout, Bout, sub_in1, sub_in2, sub_out;
	
	PIPO A(Aout, Bus, LdA, clk);
	PIPO B(Bout, Bus, LdB, clk);
	MUX21 MUX1(sub_in1, Aout, Bout, sel1);
	MUX21 MUX2(sub_in2, Aout, Bout, sel2);
	MUX21 MUX_IN(Bus, data_in, sub_out, sel_in);
	SUBTRACTOR SUB(sub_out, sub_in1, sub_in2);
	COMPARATOR COMP(lt, gt, eq, Aout, Bout); 
endmodule

Lecture26/GCD_Calculator_test_bench.v
module TEST_BENCH;
	reg[15:0] data_in;
	reg start, clk;
	wire done;
	DATAPATH DP(lt, gt, eq, data_in, LdA, LdB, sel1, sel2, sel_in, clk);
	CONTROLLER CNT(done, LdA, LdB, sel1, sel2, sel_in, start, lt, gt, eq, clk);
	
	initial begin
		clk = 1'b0;
		#3 start = 1'b1;
		#1000 $finish;
	end
	
	always #5 clk = ~clk;
	
	initial begin
		$dumpfile("GCD_Calculator.vcd");
		$dumpvars(0, TEST_BENCH);
		$monitor($time, " A = %d, B = %d, done = %b", DP.Aout, DP.Bout, done);
		#12 data_in = 39;
		#10 data_in = 143;
	end
endmodule

Lecture26/GCD_Calculator.vcd
$date
	Fri Oct  7 12:54:39 2022
$end
$version
	Icarus Verilog
$end
$timescale
	1s
$end
$scope module TEST_BENCH $end
$var wire 1 ! sel_in $end
$var wire 1 " sel2 $end
$var wire 1 # sel1 $end
$var wire 1 $ lt $end
$var wire 1 % gt $end
$var wire 1 & eq $end
$var wire 1 ' done $end
$var wire 1 ( LdB $end
$var wire 1 ) LdA $end
$var reg 1 * clk $end
$var reg 16 + data_in [15:0] $end
$var reg 1 , start $end
$scope module CNT $end
$var wire 1 * clk $end
$var wire 1 , start $end
$var wire 1 $ lt $end
$var wire 1 % gt $end
$var wire 1 & eq $end
$var reg 1 ) LdA $end
$var reg 1 ( LdB $end
$var reg 1 ' done $end
$var reg 3 - next_state [2:0] $end
$var reg 3 . present_state [2:0] $end
$var reg 1 # sel1 $end
$var reg 1 " sel2 $end
$var reg 1 ! sel_in $end
$upscope $end
$scope module DP $end
$var wire 1 ) LdA $end
$var wire 1 ( LdB $end
$var wire 1 * clk $end
$var wire 16 / data_in [15:0] $end
$var wire 1 # sel1 $end
$var wire 1 " sel2 $end
$var wire 1 ! sel_in $end
$var wire 16 0 sub_out [15:0] $end
$var wire 16 1 sub_in2 [15:0] $end
$var wire 16 2 sub_in1 [15:0] $end
$var wire 1 $ lt $end
$var wire 1 % gt $end
$var wire 1 & eq $end
$var wire 16 3 Bus [15:0] $end
$var wire 16 4 Bout [15:0] $end
$var wire 16 5 Aout [15:0] $end
$scope module A $end
$var wire 1 * clk $end
$var wire 1 ) load $end
$var wire 16 6 in [15:0] $end
$var reg 16 7 out [15:0] $end
$upscope $end
$scope module B $end
$var wire 1 * clk $end
$var wire 1 ( load $end
$var wire 16 8 in [15:0] $end
$var reg 16 9 out [15:0] $end
$upscope $end
$scope module COMP $end
$var wire 16 : in1 [15:0] $end
$var wire 16 ; in2 [15:0] $end
$var wire 1 $ lt $end
$var wire 1 % gt $end
$var wire 1 & eq $end
$upscope $end
$scope module MUX1 $end
$var wire 16 < in1 [15:0] $end
$var wire 16 = in2 [15:0] $end
$var wire 1 # sel $end
$var reg 16 > out [15:0] $end
$upscope $end
$scope module MUX2 $end
$var wire 16 ? in1 [15:0] $end
$var wire 16 @ in2 [15:0] $end
$var wire 1 " sel $end
$var reg 16 A out [15:0] $end
$upscope $end
$scope module MUX_IN $end
$var wire 16 B in1 [15:0] $end
$var wire 1 ! sel $end
$var wire 16 C in2 [15:0] $end
$var reg 16 D out [15:0] $end
$upscope $end
$scope module SUB $end
$var wire 16 E in1 [15:0] $end
$var wire 16 F in2 [15:0] $end
$var reg 16 G out [15:0] $end
$upscope $end
$upscope $end
$upscope $end
$enddefinitions $end
#0
$dumpvars
bx G
bx F
bx E
bx D
bx C
bx B
bx A
bx @
bx ?
bx >
bx =
bx <
bx ;
bx :
bx 9
bx 8
bx 7
bx 6
bx 5
bx 4
bx 3
bx 2
bx 1
bx 0
bx /
bx .
bx -
x,
bx +
0*
x)
x(
x'
x&
x%
x$
x#
x"
x!
$end
#3
0'
0(
0)
0!
0"
0#
b0 -
1,
#5
b0 .
1*
#7
1)
b1 -
#10
0*
#12
b100111 3
b100111 6
b100111 8
b100111 D
b100111 +
b100111 /
b100111 B
#15
b0 0
b0 C
b0 G
b100111 2
b100111 >
b100111 E
b100111 1
b100111 A
b100111 F
b1 .
b100111 5
b100111 7
b100111 :
b100111 <
b100111 ?
1*
#17
1(
0)
b10 -
#20
0*
#22
b10001111 3
b10001111 6
b10001111 8
b10001111 D
b10001111 +
b10001111 /
b10001111 B
#25
1$
0%
0&
b10001111 4
b10001111 9
b10001111 ;
b10001111 =
b10001111 @
b10 .
1*
#27
b1101000 0
b1101000 C
b1101000 G
b1101000 3
b1101000 6
b1101000 8
b1101000 D
b10001111 2
b10001111 >
b10001111 E
1!
1#
b11 -
#30
0*
#35
b1000001 3
b1000001 6
b1000001 8
b1000001 D
b1000001 0
b1000001 C
b1000001 G
b1101000 2
b1101000 >
b1101000 E
b11 .
b1101000 4
b1101000 9
b1101000 ;
b1101000 =
b1101000 @
1*
#40
0*
#45
b11010 3
b11010 6
b11010 8
b11010 D
b11010 0
b11010 C
b11010 G
b1000001 2
b1000001 >
b1000001 E
b1000001 4
b1000001 9
b1000001 ;
b1000001 =
b1000001 @
1*
#50
0*
#55
b1111111111110011 3
b1111111111110011 6
b1111111111110011 8
b1111111111110011 D
b1111111111110011 0
b1111111111110011 C
b1111111111110011 G
b11010 2
b11010 >
b11010 E
0$
1%
b11010 4
b11010 9
b11010 ;
b11010 =
b11010 @
1*
#57
b1101 3
b1101 6
b1101 8
b1101 D
b1101 0
b1101 C
b1101 G
b11010 1
b11010 A
b11010 F
b100111 2
b100111 >
b100111 E
0(
1)
1"
0#
b100 -
#60
0*
#65
b1111111111110011 3
b1111111111110011 6
b1111111111110011 8
b1111111111110011 D
b1111111111110011 0
b1111111111110011 C
b1111111111110011 G
b1101 2
b1101 >
b1101 E
1$
0%
b1101 5
b1101 7
b1101 :
b1101 <
b1101 ?
b100 .
1*
#67
b1101 3
b1101 6
b1101 8
b1101 D
b1101 0
b1101 C
b1101 G
b1101 1
b1101 A
b1101 F
b11010 2
b11010 >
b11010 E
1(
0)
0"
1#
b11 -
#70
0*
#75
b0 3
b0 6
b0 8
b0 D
b0 0
b0 C
b0 G
b1101 2
b1101 >
b1101 E
b11 .
0$
1&
b1101 4
b1101 9
b1101 ;
b1101 =
b1101 @
1*
#77
0(
1'
b101 -
#80
0*
#85
b101 .
1*
