Practice/SequenceDetector.v
//Detecting Sequence: 101010 (Overlapping Allowed)
module SequenceDetector(clk, rst, in_seq, out_seq);
	input clk, rst, in_seq;
	output reg out_seq;
	parameter S0 = 0, S1 = 1, S2 = 2, S3 = 3, S4 = 4, S5 = 5;
	reg[0:2] PS, NS;

	always @(posedge clk or posedge rst) begin
		if (rst)
			PS <= S0;
		else
			PS <= NS;
	end

	always @(PS, in_seq) begin
		case (PS)
			S0: begin
				NS = in_seq?S1:S0;
				out_seq = 0;
			end
			S1: begin
				NS = in_seq?S1:S2;
				out_seq = 0;
			end
			S2: begin
				NS = in_seq?S3:S0;
				out_seq = 0;
			end
			S3: begin
				NS = in_seq?S1:S4;
				out_seq = 0;
			end
			S4: begin
				NS = in_seq?S5:S0;
				out_seq = 0;
			end
			S5: begin
				NS = in_seq?S1:S4;
				out_seq = in_seq?0:1;
			end
			default: begin
				NS = S0;
				out_seq = 0;
			end
		endcase
	end
endmodule

Practice/SequenceDetector_tb.v
module SequenceDetector_tb;
	reg clk, rst, in_seq;
	wire out_seq;
	SequenceDetector dut(clk, rst, in_seq, out_seq);

	initial begin 
		clk = 1'b0;
		rst = 1'b1;
		#10 rst = 1'b0;
	end

	always #5 clk = ~clk;

	initial begin
		$dumpfile("SequenceDetector.vcd");
		$dumpvars(0, SequenceDetector_tb);
		#2 in_seq = 1'b0; #10 in_seq = 1'b1; #10 in_seq = 1'b0; #10 in_seq = 1'b1;
		#10 in_seq = 1'b0; #10 in_seq = 1'b1; #10 in_seq = 1'b0; #10 in_seq = 1'b1;
		#10 in_seq = 1'b0; #10 in_seq = 1'b1; #10 in_seq = 1'b0; #10 in_seq = 1'b1;
		#10 in_seq = 1'b0; #10 in_seq = 1'b1; #10 in_seq = 1'b0; #10 in_seq = 1'b1;
		#10 in_seq = 1'b0; #10 in_seq = 1'b1; #10 in_seq = 1'b1; #10 in_seq = 1'b1;
		#10 in_seq = 1'b0; #10 in_seq = 1'b1; #10 in_seq = 1'b0; #10 in_seq = 1'b1;
		#10 in_seq = 1'b0; #10 in_seq = 1'b0; #10 $finish;
	end
endmodule

Practice/SequenceDetector.vcd
$date
	Mon Oct  3 11:38:06 2022
$end
$version
	Icarus Verilog
$end
$timescale
	1s
$end
$scope module SequenceDetector_tb $end
$var wire 1 ! out_seq $end
$var reg 1 " clk $end
$var reg 1 # in_seq $end
$var reg 1 $ rst $end
$scope module dut $end
$var wire 1 " clk $end
$var wire 1 # in_seq $end
$var wire 1 $ rst $end
$var reg 3 % NS [0:2] $end
$var reg 3 & PS [0:2] $end
$var reg 1 ! out_seq $end
$upscope $end
$upscope $end
$enddefinitions $end
#0
$dumpvars
b0 &
b0x %
1$
x#
0"
0!
$end
#2
b0 %
0#
#5
1"
#10
0"
0$
#12
b1 %
1#
#15
b1 &
1"
#20
0"
#22
b10 %
0#
#25
b0 %
b10 &
1"
#30
0"
#32
b11 %
1#
#35
b1 %
b11 &
1"
#40
0"
#42
b100 %
0#
#45
b0 %
b100 &
1"
#50
0"
#52
b101 %
1#
#55
b1 %
b101 &
1"
#60
0"
#62
1!
b100 %
0#
#65
0!
b0 %
b100 &
1"
#70
0"
#72
b101 %
1#
#75
b1 %
b101 &
1"
#80
0"
#82
1!
b100 %
0#
#85
0!
b0 %
b100 &
1"
#90
0"
#92
b101 %
1#
#95
b1 %
b101 &
1"
#100
0"
#102
1!
b100 %
0#
#105
0!
b0 %
b100 &
1"
#110
0"
#112
b101 %
1#
#115
b1 %
b101 &
1"
#120
0"
#122
1!
b100 %
0#
#125
0!
b0 %
b100 &
1"
#130
0"
#132
b101 %
1#
#135
b1 %
b101 &
1"
#140
0"
#142
1!
b100 %
0#
#145
0!
b0 %
b100 &
1"
#150
0"
#152
b101 %
1#
#155
b1 %
b101 &
1"
#160
0"
#162
1!
b100 %
0#
#165
0!
b0 %
b100 &
1"
#170
0"
#172
b101 %
1#
#175
b1 %
b101 &
1"
#180
0"
#185
b1 &
1"
#190
0"
#195
1"
#200
0"
#202
b10 %
0#
#205
b0 %
b10 &
1"
#210
0"
#212
b11 %
1#
#215
b1 %
b11 &
1"
#220
0"
#222
b100 %
0#
#225
b0 %
b100 &
1"
#230
0"
#232
b101 %
1#
#235
b1 %
b101 &
1"
#240
0"
#242
1!
b100 %
0#
#245
0!
b0 %
b100 &
1"
#250
0"
#255
b0 &
1"
