Practice/SerialAdder.v
module SerialAdder(clk, rst, in_seq1, in_seq2, out_seq);
	input clk, rst, in_seq1, in_seq2;
	output reg out_seq;
	parameter ZERO = 0, ONE = 1;
	reg curr_carry, next_carry;

	always @(posedge clk or posedge rst) begin
		if (rst)
			curr_carry <= 0;
		else
			curr_carry <= next_carry;
	end

	always @(curr_carry or in_seq1 or in_seq2) begin
		case (curr_carry)
			ZERO: begin
				next_carry = (in_seq1 & in_seq2)?1:0;
				out_seq = (in_seq1 ^ in_seq2)?1:0;
			end
			ONE: begin
				next_carry = (in_seq1 | in_seq2)?1:0;
				out_seq = (in_seq1 ^ in_seq2)?0:1;
			end
			default: begin
				next_carry = 0;
				out_seq = 0;
			end
		endcase
	end
endmodule

Practice/SerialAdder_tb.v
module SerialAdder_tb;
	reg clk, rst, in_seq1, in_seq2;
	wire out_seq;
	SerialAdder dut(clk, rst, in_seq1, in_seq2, out_seq);

	initial begin
		clk = 1'b0;
		rst = 1'b1;
		#7 rst = 1'b0;
	end

	always #5 clk = ~clk;

	initial begin
		$dumpfile("SerialAdder.vcd");
		$dumpvars(0, SerialAdder_tb);
		#2 in_seq1 = 1'b0; in_seq2 = 1'b0;
		#10 in_seq1 = 1'b1; in_seq2 = 1'b0;
		#10 in_seq1 = 1'b0; in_seq2 = 1'b1;
		#10 in_seq1 = 1'b1; in_seq2 = 1'b1;
		#10 in_seq1 = 1'b0; in_seq2 = 1'b0;
		#10 in_seq1 = 1'b1; in_seq2 = 1'b1;
		#10 in_seq1 = 1'b1; in_seq2 = 1'b1;
		#10 in_seq1 = 1'b0; in_seq2 = 1'b1;
		#10 in_seq1 = 1'b1; in_seq2 = 1'b0;
		#10 in_seq1 = 1'b0; in_seq2 = 1'b0;
		#10 in_seq1 = 1'b0; in_seq2 = 1'b0;
		#10 $finish;
	end
endmodule

Practice/SerialAdder.vcd
$date
	Mon Oct  3 12:24:18 2022
$end
$version
	Icarus Verilog
$end
$timescale
	1s
$end
$scope module SerialAdder_tb $end
$var wire 1 ! out_seq $end
$var reg 1 " clk $end
$var reg 1 # in_seq1 $end
$var reg 1 $ in_seq2 $end
$var reg 1 % rst $end
$scope module dut $end
$var wire 1 " clk $end
$var wire 1 # in_seq1 $end
$var wire 1 $ in_seq2 $end
$var wire 1 % rst $end
$var reg 1 & curr_carry $end
$var reg 1 ' next_carry $end
$var reg 1 ! out_seq $end
$upscope $end
$upscope $end
$enddefinitions $end
#0
$dumpvars
x'
0&
1%
x$
x#
0"
x!
$end
#2
0!
0'
0$
0#
#5
1"
#7
0%
#10
0"
#12
1!
1#
#15
1"
#20
0"
#22
1$
0#
#25
1"
#30
0"
#32
0!
1'
1#
#35
1!
1&
1"
#40
0"
#42
0'
0$
0#
#45
0!
0&
1"
#50
0"
#52
1'
1$
1#
#55
1!
1&
1"
#60
0"
#65
1"
#70
0"
#72
0!
0#
#75
1"
#80
0"
#82
0$
1#
#85
1"
#90
0"
#92
1!
0'
0#
#95
0!
0&
1"
