Lecture25/UnsignedMultiplier_Controller.v
//Module for Controller
module multiplier_controller(done, ldA, ldB, decB, ldP, clrP, clk, start, eqz);
	input clk, start, eqz;
	output reg done, ldA, ldB, decB, ldP, clrP;
	parameter S0 = 0, S1 = 1, S2 = 2, S3 = 3, S4 = 4;
	reg[0:2] present_state, next_state;

	always@(posedge clk) begin
		present_state <= next_state;
	end

	always @(present_state, eqz, start) begin
		case (present_state)
			S0: begin
				#2 if (start) begin
					next_state = S1;
					done = 0; ldA = 1; ldB = 0; decB = 0; ldP = 0; clrP = 0;
				end
			end
			S1: begin
				#2 next_state = S2;
				ldA = 0; ldB = 1; clrP = 1;
			end
			S2: begin
				#2 if (eqz) begin
					next_state = S4;
					done = 1; ldA = 0; ldB = 0; decB = 0; ldP = 0; clrP = 0;
				end
				else begin
					next_state = S3;
					ldB = 0; decB = 1; ldP = 1; clrP = 0;
				end
			end
			S3: begin
				#2 if (eqz) begin
					next_state = S4;
					done = 1; ldA = 0; ldB = 0; decB = 0; ldP = 0; clrP = 0;
				end
			end
			S4: begin
				#2 next_state = S4; done = 1;
			end
			default: begin
				#2 next_state = S0;
				done = 0; ldA = 0; ldB = 0; decB = 0; ldP = 0; clrP = 0;
			end
		endcase
	end
endmodule

Lecture25/UnsignedMultiplierComparator.v
//Define 16 bit comparator
module comparator16(eqz, data_in);
	input[15:0] data_in;
	output eqz;

	assign eqz = (data_in == 0);
endmodule

Lecture25/UnsignedMultiplierAdder.v
//Defining 16 bit adder
module adder16(out, in1, in2);
	input[15:0] in1, in2;
	output reg[15:0] out;

	always @(*) begin
		out = in1 + in2;
	end
endmodule

Lecture25/UnsignedMultiplier_Registerwithclear.v
//Defining PIPO2 Register
module pipo2(data_out, data_in, load, clear, clk);
	input[15:0] data_in;
	input load, clk, clear;
	output reg[15:0] data_out;

	always @(posedge clk) begin
		if (clear)
			data_out <= 0;
		else if (load)
			data_out <= data_in;
	end
endmodule

Lecture25/UnsignedMultiplier_DownCounter.v
//Defining DownCounter
module downcounter(out, in, load, dec, clk);
	input[15:0] in;
	input load, dec, clk;
	output reg[15:0] out;

	always @(posedge clk) begin
		if (dec)
			out <= out - 1;
		else if (load)
			out <= in;
	end
endmodule

Lecture25/UnsignedMultiplier_Registerwithoutclear.v
//Defining PIPO1 Register
module pipo1(data_out, data_in, load, clk);
	input[15:0] data_in;
	input load, clk;
	output reg[15:0] data_out;

	always @(posedge clk) begin
		if (load)
			data_out <= data_in;
	end
endmodule

Lecture25/UnsignedMultiplierDataPath.v
//Main Module for Data Path
module multiplier_data_path(eqz, data_in, clk, ldA, ldB, decB, ldP, clrP);
	input[15:0] data_in;
	input clk, ldA, ldB, decB, ldP, clrP;
	output eqz;
	wire[15:0] X, Y, Z, Bus, Bout;

	assign Bus = data_in;

	//Module Instantiations
	pipo1 A(X, Bus, ldA, clk);
	downcounter B(Bout, Bus, ldB, decB, clk);
	pipo2 P(Y, Z, ldP, clrP, clk);
	adder16 ADD(Z, X, Y);
	comparator16 COMP(eqz, Bout);
endmodule

Lecture25/UnsignedMultiplier_tb.v
//Test Bench for 16 bit Unsigned Multiplier
module multiplier_test_bench;
	reg[15:0] data_in;
	reg start, clk;
	wire done;

	multiplier_data_path dp(eqz, data_in, clk, ldA, ldB, decB, ldP, clrP);
	multiplier_controller controller(done, ldA, ldB, decB, ldP, clrP, clk, start, eqz);

	initial begin
		clk = 1'b0;
		#3 start = 1'b1;
		#1000 $finish;
	end

	always #5 clk = ~clk;

	initial begin
		$dumpfile("UnsignedMultiplier.vcd");
		$dumpvars(0, multiplier_test_bench);
		$monitor($time, " A = %d, B = %d, Product = %d, done = %b, eqz = %b, Present State = %d", dp.X, dp.Bout, dp.Y, done, controller.eqz, controller.present_state);
		#13 data_in = 18;
		#10 data_in = 7;
	end
endmodule

Lecture25/UnsignedMultiplier.vcd
$date
	Wed Oct  5 09:57:21 2022
$end
$version
	Icarus Verilog
$end
$timescale
	1s
$end
$scope module multiplier_test_bench $end
$var wire 1 ! ldP $end
$var wire 1 " ldB $end
$var wire 1 # ldA $end
$var wire 1 $ eqz $end
$var wire 1 % done $end
$var wire 1 & decB $end
$var wire 1 ' clrP $end
$var reg 1 ( clk $end
$var reg 16 ) data_in [15:0] $end
$var reg 1 * start $end
$scope module controller $end
$var wire 1 ( clk $end
$var wire 1 * start $end
$var wire 1 $ eqz $end
$var reg 1 ' clrP $end
$var reg 1 & decB $end
$var reg 1 % done $end
$var reg 1 # ldA $end
$var reg 1 " ldB $end
$var reg 1 ! ldP $end
$var reg 3 + next_state [0:2] $end
$var reg 3 , present_state [0:2] $end
$upscope $end
$scope module dp $end
$var wire 16 - Bus [15:0] $end
$var wire 1 ( clk $end
$var wire 1 ' clrP $end
$var wire 16 . data_in [15:0] $end
$var wire 1 & decB $end
$var wire 1 # ldA $end
$var wire 1 " ldB $end
$var wire 1 ! ldP $end
$var wire 1 $ eqz $end
$var wire 16 / Z [15:0] $end
$var wire 16 0 Y [15:0] $end
$var wire 16 1 X [15:0] $end
$var wire 16 2 Bout [15:0] $end
$scope module A $end
$var wire 1 ( clk $end
$var wire 16 3 data_in [15:0] $end
$var wire 1 # load $end
$var reg 16 4 data_out [15:0] $end
$upscope $end
$scope module ADD $end
$var wire 16 5 in1 [15:0] $end
$var wire 16 6 in2 [15:0] $end
$var reg 16 7 out [15:0] $end
$upscope $end
$scope module B $end
$var wire 1 ( clk $end
$var wire 1 & dec $end
$var wire 16 8 in [15:0] $end
$var wire 1 " load $end
$var reg 16 9 out [15:0] $end
$upscope $end
$scope module COMP $end
$var wire 16 : data_in [15:0] $end
$var wire 1 $ eqz $end
$upscope $end
$scope module P $end
$var wire 1 ' clear $end
$var wire 1 ( clk $end
$var wire 16 ; data_in [15:0] $end
$var wire 1 ! load $end
$var reg 16 < data_out [15:0] $end
$upscope $end
$upscope $end
$upscope $end
$enddefinitions $end
#0
$dumpvars
bx <
bx ;
bx :
bx 9
bx 8
bx 7
bx 6
bx 5
bx 4
bx 3
bx 2
bx 1
bx 0
bx /
bx .
bx -
bx ,
bx +
x*
bx )
0(
x'
x&
x%
x$
x#
x"
x!
$end
#3
1*
#5
b0 ,
0'
0!
0&
0"
0#
0%
b0 +
1(
#7
1#
b1 +
#10
0(
#13
b10010 -
b10010 3
b10010 8
b10010 )
b10010 .
#15
b1 ,
b10010 1
b10010 4
b10010 5
1(
#17
1'
1"
0#
b10 +
#20
0(
#23
b111 -
b111 3
b111 8
b111 )
b111 .
#25
b10010 /
b10010 7
b10010 ;
0$
b111 2
b111 9
b111 :
b0 0
b0 6
b0 <
b10 ,
1(
#27
0'
1!
1&
0"
b11 +
#30
0(
#35
b100100 /
b100100 7
b100100 ;
b11 ,
b10010 0
b10010 6
b10010 <
b110 2
b110 9
b110 :
1(
#40
0(
#45
b110110 /
b110110 7
b110110 ;
b101 2
b101 9
b101 :
b100100 0
b100100 6
b100100 <
1(
#50
0(
#55
b1001000 /
b1001000 7
b1001000 ;
b110110 0
b110110 6
b110110 <
b100 2
b100 9
b100 :
1(
#60
0(
#65
b1011010 /
b1011010 7
b1011010 ;
b11 2
b11 9
b11 :
b1001000 0
b1001000 6
b1001000 <
1(
#70
0(
#75
b1101100 /
b1101100 7
b1101100 ;
b1011010 0
b1011010 6
b1011010 <
b10 2
b10 9
b10 :
1(
#80
0(
#85
b1111110 /
b1111110 7
b1111110 ;
b1 2
b1 9
b1 :
b1101100 0
b1101100 6
b1101100 <
1(
#90
0(
#95
b10010000 /
b10010000 7
b10010000 ;
b1111110 0
b1111110 6
b1111110 <
1$
b0 2
b0 9
b0 :
1(
#97
0!
0&
1%
b100 +
#100
0(
#105
b100 ,
1(
