Lecture24/ParityDetector.v
module ParityDetector(clk, in_seq, out_seq);
	input clk, in_seq;
	output reg out_seq;
	reg state;
	parameter EVEN = 0, ODD= 1;

	always @(posedge clk)
		case (state)
			EVEN: state <= in_seq?ODD:EVEN;
			ODD: state <= in_seq?EVEN:ODD;
			default: state <= EVEN;
		endcase
		always @(state) begin
			case(state)
				EVEN: out_seq = 0;
				ODD: out_seq = 1;
			endcase
		end
endmodule

Lecture24/ParityDetector_tb.v
module Parity_Detector_tb;
	reg in_seq, clk;
	wire out_seq;

	ParityDetector dut(clk, in_seq, out_seq);

	initial clk = 1'b0;
	always #5 clk = ~clk;
	initial begin
		$dumpfile("ParityDetector.vcd");
		$dumpvars(0, Parity_Detector_tb);
		$monitor($time, ": in_seq = %b, out_seq = %b", in_seq, out_seq);
		#2 in_seq = 0; #10 in_seq = 1; #10 in_seq = 1; #10 in_seq = 0;
		#10 in_seq = 1; #10 in_seq = 1; #10 in_seq = 1; #10 in_seq = 1;
		#10 in_seq = 0; #10 in_seq = 0; #10 in_seq = 0; #10 in_seq = 1;
		#10 $finish;
	end
endmodule

Lecture24/ParityDetector.vcd
$date
	Fri Sep 30 16:07:38 2022
$end
$version
	Icarus Verilog
$end
$timescale
	1s
$end
$scope module Parity_Detector_tb $end
$var wire 1 ! out_seq $end
$var reg 1 " clk $end
$var reg 1 # in_seq $end
$scope module dut $end
$var wire 1 " clk $end
$var wire 1 # in_seq $end
$var reg 1 ! out_seq $end
$var reg 1 $ state $end
$upscope $end
$upscope $end
$enddefinitions $end
#0
$dumpvars
x$
x#
0"
x!
$end
#2
0#
#5
0!
0$
1"
#10
0"
#12
1#
#15
1!
1$
1"
#20
0"
#25
0!
0$
1"
#30
0"
#32
0#
#35
1"
#40
0"
#42
1#
#45
1!
1$
1"
#50
0"
#55
0!
0$
1"
#60
0"
#65
1!
1$
1"
#70
0"
#75
0!
0$
1"
#80
0"
#82
0#
#85
1"
#90
0"
#95
1"
#100
0"
#105
1"
#110
0"
#112
1#
#115
1!
1$
1"
