Lecture24/SequenceDetector.v
//Detected Sequence: 0110 (Overlapping patterns are also detected)
module SequenceDetector(clk, rst, in_seq, out_seq);
	input clk, in_seq, rst;
	output reg out_seq;
	parameter S0 = 0, S1 = 1, S2 = 2, S3 = 3;
	reg[0:1] NS, PS;
	
	initial begin
		$monitor($time, ": Next State = %b, Present State = %b", NS, PS);
	end
	
	always @(posedge clk or posedge rst) begin
		if (rst)
			PS <= S0;
		else
			PS <= NS;
	end
	
	always @(PS, in_seq) begin
		case (PS)
			S0: begin
				NS = in_seq?S0:S1;
				out_seq = 0;
			end
			S1: begin
				NS = in_seq?S2:S1;
				out_seq = 0;
			end
			S2: begin
				NS = in_seq?S3:S1;
				out_seq = 0;
			end
			S3: begin
				NS = in_seq?S0:S1;
				out_seq = in_seq?0:1;
			end
			default: begin
				NS = S0;
				out_seq = 0;
			end
		endcase
	end
endmodule

Lecture24/SequenceDetector_tb.v
module SequenceDetector_tb;
	reg clk, rst, in_seq;
	wire out_seq;
	SequenceDetector dut(clk, rst, in_seq, out_seq);

	initial begin
		clk = 1'b0;
		rst = 1'b1;
		#13 rst = 1'b0;
	end
	
	always #5 clk = ~clk;

	initial begin
		$dumpfile("SequenceDetector.vcd");
		$dumpvars(0, SequenceDetector_tb);
		#12 in_seq = 0; #10 in_seq = 0; #10 in_seq = 1; #10 in_seq = 1;
		#10 in_seq = 0; #10 in_seq = 1; #10 in_seq = 1; #10 in_seq = 0;
		#10 in_seq = 0; #10 in_seq = 1; #10 in_seq = 1; #10 in_seq = 0;
		#10 $finish;
	end
endmodule

Lecture24/SequenceDetector.vcd
$date
	Fri Sep 30 16:48:56 2022
$end
$version
	Icarus Verilog
$end
$timescale
	1s
$end
$scope module SequenceDetector_tb $end
$var wire 1 ! out_seq $end
$var reg 1 " clk $end
$var reg 1 # in_seq $end
$var reg 1 $ rst $end
$scope module dut $end
$var wire 1 " clk $end
$var wire 1 # in_seq $end
$var wire 1 $ rst $end
$var reg 2 % NS [0:1] $end
$var reg 2 & PS [0:1] $end
$var reg 1 ! out_seq $end
$upscope $end
$upscope $end
$enddefinitions $end
#0
$dumpvars
b0 &
b0x %
1$
x#
0"
0!
$end
#5
1"
#10
0"
#12
b1 %
0#
#13
0$
#15
b1 &
1"
#20
0"
#25
1"
#30
0"
#32
b10 %
1#
#35
b11 %
b10 &
1"
#40
0"
#45
b0 %
b11 &
1"
#50
0"
#52
1!
b1 %
0#
#55
0!
b1 &
1"
#60
0"
#62
b10 %
1#
#65
b11 %
b10 &
1"
#70
0"
#75
b0 %
b11 &
1"
#80
0"
#82
1!
b1 %
0#
#85
0!
b1 &
1"
#90
0"
#95
1"
#100
0"
#102
b10 %
1#
#105
b11 %
b10 &
1"
#110
0"
#115
b0 %
b11 &
1"
#120
0"
#122
1!
b1 %
0#
#125
0!
b1 &
1"
