Lecture23/MooreMachine_optimized.v
module MooreMachine_optimized(clk, out);
	input clk;
	output reg[0:2] out;
	parameter S0 = 0, S1 = 1, S2 = 2;
	parameter RED = 3'b100, GREEN = 3'b010, YELLOW = 3'b001;
	reg[0:1] state;

	always@(posedge clk) begin
		case (state)
			S0: state <= S1;
			S1: state <= S2;
			S2: state <= S0;
			default: state <= S0;
		endcase
	end
	always@(state) begin
		case (state)
			S0: out = RED;
			S1: out = GREEN;
			S2: out = YELLOW;
			default: out = RED;
		endcase
	end
endmodule

Lecture23/MooreMachine_tb.v
module MooreMachine_tb;
	reg clk;
	wire[0:2] out;

	MooreMachine_optimized dut(clk, out);

	initial clk = 1'b0;

	always clk = #5 ~clk;

	initial begin
		$dumpfile("MooreMachine.vcd");
		$dumpvars(0, MooreMachine_tb);
		$monitor($time, " RGY = %b", out);
		#100 $finish;
	end
endmodule

Lecture23/MooreMachine.vcd
$date
	Thu Sep 29 16:07:42 2022
$end
$version
	Icarus Verilog
$end
$timescale
	1s
$end
$scope module MooreMachine_tb $end
$var wire 3 ! out [0:2] $end
$var reg 1 " clk $end
$scope module dut $end
$var wire 1 " clk $end
$var reg 3 # out [0:2] $end
$var reg 2 $ state [0:1] $end
$upscope $end
$upscope $end
$enddefinitions $end
#0
$dumpvars
bx $
bx #
0"
bx !
$end
#5
b100 !
b100 #
b0 $
1"
#10
0"
#15
b10 !
b10 #
b1 $
1"
#20
0"
#25
b1 !
b1 #
b10 $
1"
#30
0"
#35
b100 !
b100 #
b0 $
1"
#40
0"
#45
b10 !
b10 #
b1 $
1"
#50
0"
#55
b1 !
b1 #
b10 $
1"
#60
0"
#65
b100 !
b100 #
b0 $
1"
#70
0"
#75
b10 !
b10 #
b1 $
1"
#80
0"
#85
b1 !
b1 #
b10 $
1"
#90
0"
#95
b100 !
b100 #
b0 $
1"
