Lecture17/RingCounter.v
module ring_counter(init, clk, count);
	input init, clk;
	output reg[7:0] count;
	
	always @(posedge clk)
		if (init)
			count <= 8'b10000000;
		else
			begin
				count <= count >> 1;
				count[7] <= count[0];
			end
endmodule

Lecture17/ring_counter_tb.v
module ring_counter_tb;
	reg init, clk;
	wire[7:0] count;
	
	//Instantiate the Ring Counter
	ring_counter my_counter(init, clk, count);
	
	//Put init to 1 at the start for initialization
	initial begin
		init = 1;
		#10 init = 0;
	end
	
	//Generate the Clock Signal
	initial begin
		clk = 0;
		forever
			#5 clk = ~clk;
	end
	
	//Monitor the Count Value and Specify When To Finish
	initial begin
		$dumpfile("output.vcd");
		$dumpvars(0, ring_counter_tb);
		$monitor($time, " : init = %b, count = %8b", init, count);
		#90 $finish;
	end
endmodule

Lecture17/output.vcd
$date
	Wed May  4 17:20:04 2022
$end
$version
	Icarus Verilog
$end
$timescale
	1s
$end
$scope module ring_counter_tb $end
$var wire 8 ! count [7:0] $end
$var reg 1 " clk $end
$var reg 1 # init $end
$scope module my_counter $end
$var wire 1 " clk $end
$var wire 1 # init $end
$var reg 8 $ count [7:0] $end
$upscope $end
$upscope $end
$enddefinitions $end
#0
$dumpvars
bx $
1#
0"
bx !
$end
#5
b10000000 !
b10000000 $
1"
#10
0"
0#
#15
b1000000 !
b1000000 $
1"
#20
0"
#25
b100000 !
b100000 $
1"
#30
0"
#35
b10000 !
b10000 $
1"
#40
0"
#45
b1000 !
b1000 $
1"
#50
0"
#55
b100 !
b100 $
1"
#60
0"
#65
b10 !
b10 $
1"
#70
0"
#75
b1 !
b1 $
1"
#80
0"
#85
b10000000 !
b10000000 $
1"
